{
  "sample_index": 9,
  "session_id": 826,
  "gold_label": "Normal",
  "situation": "my boss does not care about my and there is no guidance complete ignorance due to the fact that I am",
  "initial_detection": {
    "predicted_label": "normal",
    "confidence": 0.9996088147163391,
    "all_probabilities": {
      "normal": 0.9996088147163391,
      "v1": 7.56301378714852e-05,
      "v2": 3.006781480507925e-05,
      "v3": 6.386059976648539e-05,
      "v4": 3.8116108044050634e-05,
      "v5": 0.00018361172988079488
    },
    "severity": 0
  },
  "timing": {
    "context_build_ms": 4.4,
    "generation_ms": 1461.7,
    "detection_ms": 31.6,
    "rewrite_total_ms": 0.0,
    "total_ms": 1497.8
  },
  "rewrite_iterations": [],
  "final_result": {
    "label": "normal",
    "response": "That sounds really frustrating and disheartening. Have you thought about how you might present your concerns to HR? Maybe listing specific examples of your workload and how it differs from your colleagues could help make your case clearer. Would you feel comfortable preparing a few points to discuss?",
    "total_retries": 0,
    "used_failsafe": false
  }
}